server_tables/__init__.py
server_tables/fields.py
server_tables/metadata.py
server_tables/views.py
django_server_tables-0.1.3.dist-info/METADATA
django_server_tables-0.1.3.dist-info/WHEEL
django_server_tables-0.1.3.dist-info/LICENSE
django_server_tables-0.1.3.dist-info/RECORD
