Metadata-Version: 2.1
Name: django-server-tables
Version: 0.1.3
Summary: Utils to configure tables data on the server.
Home-page: https://github.com/Agro-Club/django-server-tables
License: MIT
Author: egrvdaniil
Author-email: d.egorov@agro.club
Requires-Python: >=3.10,<4.0
Classifier: Framework :: Django
Classifier: Intended Audience :: Developers
Classifier: License :: OSI Approved :: MIT License
Classifier: Operating System :: OS Independent
Classifier: Programming Language :: Python :: 3
Classifier: Programming Language :: Python :: 3.10
Classifier: Programming Language :: Python :: 3.11
Classifier: Programming Language :: Python :: 3 :: Only
Classifier: Programming Language :: Python :: 3.10
Classifier: Programming Language :: Python :: 3.11
Classifier: Programming Language :: Python :: 3.8
Classifier: Programming Language :: Python :: 3.9
Classifier: Topic :: Software Development
Requires-Dist: django-filter (>=22.1,<23.0)
Requires-Dist: djangorestframework (>=3.14.0,<4.0.0)
Project-URL: Documentation, https://github.com/Agro-Club/django-server-tables
Project-URL: Repository, https://github.com/Agro-Club/django-server-tables
